scbw/__init__.py
scbw/__main__.py
scbw/bot_factory.py
scbw/bot_storage.py
scbw/bwapi.py
scbw/cli.py
scbw/defaults.py
scbw/docker.py
scbw/docker_utils.py
scbw/error.py
scbw/game.py
scbw/game_type.py
scbw/install.py
scbw/logs.py
scbw/map.py
scbw/player.py
scbw/plot.py
scbw/result.py
scbw/utils.py
scbw/vnc.py
scbw/local_docker/default.mpc
scbw/local_docker/default.spc
scbw/local_docker/game.dockerfile
scbw/local_docker/player.mpc
scbw/local_docker/player.spc
scbw-1.0.4.dist-info/DESCRIPTION.rst
scbw-1.0.4.dist-info/METADATA
scbw-1.0.4.dist-info/RECORD
scbw-1.0.4.dist-info/WHEEL
scbw-1.0.4.dist-info/entry_points.txt
scbw-1.0.4.dist-info/metadata.json
scbw-1.0.4.dist-info/top_level.txt
